epicview
