Metadata-Version: 2.1
Name: epicview
Version: 0.2.3
Summary: EPIC viewer application.
Home-page: https://github.com/epicsuite/epicview
Author: David H. Rogers
Author-email: dhr@lanl.gov
Classifier: Programming Language :: Python :: 3
Classifier: License :: OSI Approved :: BSD License
Classifier: Operating System :: OS Independent
Requires-Dist: trame
Requires-Dist: trame-vuetify
Requires-Dist: trame-vtk
Requires-Dist: vtk
Requires-Dist: pandas
Requires-Dist: pyyaml
